{
  "case_number": "CGC19578160",
  "case_title": "PORTFOLIO RECOVERY ASSOCIATES LLC VS. ASH KAELIN",
  "court": "SF Superior",
  "cause_of_action": "EXEMPT COLLECTIONS (RULE 3.740)",
  "captured_at": "2026-06-20T00:00:51.681Z",
  "source_url": "https://webapps.sftc.org/ci/CaseInfo.dll?CaseNum=CGC19578160&SessionID=FD5E3A49F495E5720079D06FD3EB3354838901FC",
  "docket_entries": [
    {
      "date_filed": "2020-03-13 15:20:13",
      "description": "DISMISSAL OF ENTIRE ACTION OF ALL PARTIES AND ALL CAUSES OF ACTION WITHOUT PREJUDICE (TRANSACTION ID # 100099682)",
      "doc_id": "07204650",
      "has_document": true,
      "fee": ""
    },
    {
      "date_filed": "2019-08-06 10:15:13",
      "description": "EXEMPT COLLECTIONS (RULE 3.740), COMPLAINT FILED BY PLAINTIFF PORTFOLIO RECOVERY ASSOCIATES LLC AS TO DEFENDANT KAELIN, ASH SUMMONS ISSUED, JUDICIAL COUNCIL CIVIL CASE COVER SHEET FILED PROOF OF SERVICE DUE ON                  FEB-03-2020",
      "doc_id": "06929819",
      "has_document": true,
      "fee": "$225.00"
    },
    {
      "date_filed": "2020-02-13 08:46:27",
      "description": "ORDER TO SHOW CAUSE SET FOR MAR-24-2020 IN DEPARTMENT 610 AT 10:30 AM FOR FAILURE TO FILE PROOF(S) OF SERVICE ON DEFENDANT(S) OF SUMMONS AND COMPLAINT. NOTICE SENT BY COURT.",
      "doc_id": "07163986",
      "has_document": true,
      "fee": ""
    },
    {
      "date_filed": "2020-03-17 15:53:32",
      "description": "ORDER TO SHOW CAUSE OF MAR-24-2020 IS OFF CALENDAR. DISMISSAL ON FILE. NOTICE SENT BY COURT.",
      "doc_id": "07207642",
      "has_document": true,
      "fee": ""
    }
  ],
  "documents": [
    {
      "doc_id": "07204650",
      "description": "DISMISSAL OF ENTIRE ACTION OF ALL PARTIES AND ALL CAUSES OF ACTION WITHOUT PREJUDICE (TRANSACTION ID # 100099682)",
      "filed": "2020-03-13",
      "is_available": true,
      "sha256": null,
      "byte_capture_deferred": true,
      "byte_capture_deferred_reason": "docket_only_mass_scan_requested",
      "byte_capture_scope": "docket-only"
    },
    {
      "doc_id": "06929819",
      "description": "EXEMPT COLLECTIONS (RULE 3.740), COMPLAINT FILED BY PLAINTIFF PORTFOLIO RECOVERY ASSOCIATES LLC AS TO DEFENDANT KAELIN, ASH SUMMONS ISSUED, JUDICIAL COUNCIL CIVIL CASE COVER SHEET FILED PROOF OF SERVICE DUE ON                  FEB-03-2020",
      "filed": "2019-08-06",
      "is_available": true,
      "sha256": null,
      "byte_capture_deferred": true,
      "byte_capture_deferred_reason": "docket_only_mass_scan_requested",
      "byte_capture_scope": "docket-only"
    },
    {
      "doc_id": "07163986",
      "description": "ORDER TO SHOW CAUSE SET FOR MAR-24-2020 IN DEPARTMENT 610 AT 10:30 AM FOR FAILURE TO FILE PROOF(S) OF SERVICE ON DEFENDANT(S) OF SUMMONS AND COMPLAINT. NOTICE SENT BY COURT.",
      "filed": "2020-02-13",
      "is_available": true,
      "sha256": null,
      "byte_capture_deferred": true,
      "byte_capture_deferred_reason": "docket_only_mass_scan_requested",
      "byte_capture_scope": "docket-only"
    },
    {
      "doc_id": "07207642",
      "description": "ORDER TO SHOW CAUSE OF MAR-24-2020 IS OFF CALENDAR. DISMISSAL ON FILE. NOTICE SENT BY COURT.",
      "filed": "2020-03-17",
      "is_available": true,
      "sha256": null,
      "byte_capture_deferred": true,
      "byte_capture_deferred_reason": "docket_only_mass_scan_requested",
      "byte_capture_scope": "docket-only"
    }
  ],
  "parties": [
    {
      "name": "KAELIN, ASH",
      "party_type": "DEFENDANT",
      "attorneys": [],
      "self_represented": false
    },
    {
      "name": "PORTFOLIO RECOVERY ASSOCIATES LLC",
      "party_type": "PLAINTIFF",
      "attorneys": [
        "HUNT, MICHAEL SCOTT"
      ],
      "self_represented": false
    }
  ],
  "attorneys": [
    {
      "name": "HUNT, MICHAEL SCOTT",
      "bar_number": "099804",
      "address": "HUNT & HENRIQUES ATTORNEYS AT LAW, 151 BERNAL ROAD STE 8, SAN JOSE, CA 951191306, 408-362-2270",
      "parties_represented": [
        "PORTFOLIO RECOVERY ASSOCIATES LLC (PLAINTIFF)"
      ]
    }
  ],
  "calendar": [
    {
      "court_date": "2020-03-24 10:30 AM",
      "matters": "ORDER TO SHOW CAUSE<br>Off Calendar Mar-17-2020 Off Calendar",
      "location": "CIVIC CENTER COURTHOUSE ROOM 610",
      "judge": "GARRETT L. WONG"
    }
  ],
  "payments": [
    {
      "date": "2019-08-06",
      "amount": 225,
      "type": "CHECK",
      "receipt": "W1019806F005",
      "description": "COMPLAINT/PETITION/FIRST PAPER"
    }
  ],
  "payments_total": 225,
  "method_status": {
    "GetAttorneys": "ok",
    "GetCalendar": "ok",
    "GetDocuments": "ok",
    "GetPayments": "ok",
    "GetROA": "ok",
    "GetParties": "ok"
  },
  "document_bytes_captured": true,
  "document_byte_capture_scope": "docket-only",
  "documents_bytes_count": 0,
  "documents_unavailable_count": 0,
  "documents_deferred_count": 4
}
