{
  "case_number": "CPF12022672",
  "case_title": "IN RE: VERNON FRISON",
  "court": "SF Superior",
  "cause_of_action": "CLAIM OPPOSING FORFEITURE",
  "captured_at": "2026-06-21T15:43:13.408Z",
  "source_url": "https://webapps.sftc.org/ci/CaseInfo.dll?CaseNum=CPF12022672&SessionID=B6900AE1543116836E7A01499E18795B785F98D2",
  "docket_entries": [
    {
      "date_filed": "2012-06-22 09:36:26",
      "description": "PETITION $9,821. FILED BY CLAIMANT FRISON, VERNON",
      "doc_id": null,
      "has_document": false,
      "fee": ""
    },
    {
      "date_filed": "2012-06-22 09:42:01",
      "description": "UNLIMITED FILING FEES $410.00 FILED BY CLAIMANT FRISON, VERNON",
      "doc_id": null,
      "has_document": false,
      "fee": "$410.00"
    }
  ],
  "documents": [],
  "parties": [
    {
      "name": "FRISON, VERNON",
      "party_type": "CLAIMANT",
      "attorneys": [
        "FITCH, ANGELI RAVEN"
      ],
      "self_represented": false
    }
  ],
  "attorneys": [
    {
      "name": "FITCH, ANGELI RAVEN",
      "bar_number": "231943",
      "address": "855 BRYANT STREET #201, SAN FRANCISCO, CA 94103, 415-913-7742",
      "parties_represented": [
        "FRISON, VERNON (CLAIMANT)"
      ]
    }
  ],
  "calendar": [],
  "payments": [
    {
      "date": "2012-06-22",
      "amount": 410,
      "type": "CHECK",
      "receipt": "W1012622F004",
      "description": "CIVIL COMPLAINT/PETITION/OTHER FIRST PAPER"
    }
  ],
  "payments_total": 410,
  "method_status": {
    "GetAttorneys": "ok",
    "GetParties": "ok",
    "GetDocuments": "zero",
    "GetCalendar": "zero",
    "GetPayments": "ok",
    "GetROA": "ok"
  },
  "document_bytes_captured": true,
  "documents_bytes_count": 0,
  "documents_deferred_count": 0,
  "document_byte_capture_scope": "docket-only",
  "documents_unavailable_count": 0
}
