{
  "case_number": "CUD18660904",
  "case_title": "THE TIDES CENTER VS. LISA COOPER ET AL",
  "court": "SF Superior",
  "cause_of_action": "UNLAWFUL DETAINER - RESIDENTIAL",
  "captured_at": "2026-06-20T00:06:47.511Z",
  "source_url": "https://webapps.sftc.org/ci/CaseInfo.dll?CaseNum=CUD18660904&SessionID=74795A014FD182FA9E6D4F70B25F49AA43D53407",
  "docket_entries": [
    {
      "date_filed": "2018-04-13 13:03:16",
      "description": "EXECUTION FOR POSSESSION OF REAL PROPERTY ISSUED TO SAN FRANCISCO COUNTY AS TO DEFENDANT COOPER, LISA",
      "doc_id": null,
      "has_document": false,
      "fee": "$25.00"
    },
    {
      "date_filed": "2018-01-25 09:55:01",
      "description": "NOTICE TO DEFENDANTS",
      "doc_id": "06192038",
      "has_document": true,
      "fee": ""
    },
    {
      "date_filed": "2018-04-13 13:02:26",
      "description": "DECLARATION OF FAIR RENTAL VALUE OF THE PREMISE WAS $15.26 FILED BY PLAINTIFF THE TIDES CENTER",
      "doc_id": "06295530",
      "has_document": true,
      "fee": ""
    },
    {
      "date_filed": "2018-01-29 09:33:55",
      "description": "REQUEST TO WAIVE JURY FEES AND EXPENSES PURSUANT TO G.C. 68633, CRC 3.51, 8.26, AND 8.818 (CONFIDENTIAL) FILED BY DEFENDANT COOPER, LISA ORDER FOR WAIVER OF JURY FEES AND EXPENSES GRANTED PURSUANT TO G.C. 68634 (E), CRC 3.52",
      "doc_id": null,
      "has_document": false,
      "fee": ""
    },
    {
      "date_filed": "2018-02-21 14:32:27",
      "description": "NOTICE OF LIMITED SCOPE REPRESENTATION, U.D. SETTLEMENT CONFERENCE AT 2/21/18 MANDATORY SETTLEMENT CONFERENCE FILED BY DEFENDANT COOPER, LISA KATAYAMA, ERIN ASSIGNED TO REPRESENT PARTY FOR U. D. SETTLEMENT CONFERENCE",
      "doc_id": "06225956",
      "has_document": true,
      "fee": ""
    },
    {
      "date_filed": "2018-01-29 09:34:08",
      "description": "ANSWER TO COMPLAINT FILED BY DEFENDANT COOPER, LISA",
      "doc_id": "06195537",
      "has_document": true,
      "fee": "IFP"
    },
    {
      "date_filed": "2018-01-29 09:32:33",
      "description": "REQUEST TO WAIVE COURT FEES AND COSTS PURSUANT TO G.C. 68633, CRC 3.51, 8.26, AND 8.818 (CONFIDENTIAL) FILED BY DEFENDANT COOPER, LISA ORDER FOR WAIVER OF COURT FEES AND COSTS GRANTED PURSUANT TO G.C. 68634 (E), CRC 3.52",
      "doc_id": null,
      "has_document": false,
      "fee": ""
    },
    {
      "date_filed": "2018-01-29 09:34:09",
      "description": "DEMAND FOR JURY FILED BY DEFENDANT COOPER, LISA",
      "doc_id": "06195538",
      "has_document": true,
      "fee": ""
    },
    {
      "date_filed": "2018-02-06 15:06:24",
      "description": "DEMAND FOR JURY ON REQUEST TO SET CASE FOR JURY TRIAL FILED BY PLAINTIFF THE TIDES CENTER HEARING SET FOR FEB-26-2018 AT 09:00 AM IN DEPT 501",
      "doc_id": "06207991",
      "has_document": true,
      "fee": ""
    },
    {
      "date_filed": "2018-02-06 15:06:25",
      "description": "NOTICE OF TIME AND PLACE OF TRIAL AND SETTLEMENT HEARING HEARING SET FOR FEB-21-2018 AT 01:30 PM IN DEPT 501",
      "doc_id": "06207992",
      "has_document": true,
      "fee": ""
    },
    {
      "date_filed": "2018-02-21 09:07:46",
      "description": "STIPULATION FOR ENTRY OF JUDGMENT FILED BY PLAINTIFF THE TIDES CENTER ALSO FILED BY DEFENDANT COOPER, LISA",
      "doc_id": "06226837",
      "has_document": true,
      "fee": ""
    },
    {
      "date_filed": "2018-03-09 10:24:19",
      "description": "DECLARATION OF LISA COOPER FILED BY DEFENDANT COOPER, LISA",
      "doc_id": "06247863",
      "has_document": true,
      "fee": ""
    },
    {
      "date_filed": "2018-03-23 10:55:35",
      "description": "ORDER GRANTING PLAINTIFF'S EX PARTE APPLICATION FOR JUDGMENT",
      "doc_id": "06263111",
      "has_document": true,
      "fee": ""
    },
    {
      "date_filed": "2018-03-23 11:05:38",
      "description": "THE COURT ORDERED THE FOLLOWING JUDGMENT ENTERED: IT IS ADJUDGED THAT PLAINTIFF THE TIDES CENTER RECOVER FROM DEFENDANT COOPER, LISA THE RESTITUTION AND POSSESSION OF THE PREMISES: 520 JONES STREET, #709, CITY AND COUNTY OF SAN FRANCISCO, CA 94102 $1,588.44 RENT, TOTAL JUDGMENT $1,588.44, LEASE FORFEITED, SEE SCANNED DOC",
      "doc_id": "06263170",
      "has_document": true,
      "fee": ""
    },
    {
      "date_filed": "2018-04-02 16:16:36",
      "description": "NOTICE OF ENTRY OF ORDER/NOTICE OF RULING FILED GRANTING EX PARTE APPL FOR JUDGMNT FILED BY PLAINTIFF THE TIDES CENTER",
      "doc_id": "06278451",
      "has_document": true,
      "fee": ""
    },
    {
      "date_filed": "2018-05-09 11:16:02",
      "description": "RETURN OF EXECUTION FOR POSSESSION OF REAL PROPERTY ISSUED TO SAN FRANCISCO COUNTY, RETURNED AND FILED, SATISFIED AS TO REAL PROPERTY ONLY AS TO DEFENDANT COOPER, LISA",
      "doc_id": "06330530",
      "has_document": true,
      "fee": ""
    },
    {
      "date_filed": "2018-01-25 09:55:00",
      "description": "UNLAWFUL DETAINER - RESIDENTIAL, COMPLAINT FILED BY PLAINTIFF THE TIDES CENTER AS TO DEFENDANT COOPER, LISA DOES 1 TO 5 SUMMONS ISSUED, JUDICIAL COUNCIL CIVIL CASE COVER SHEET FILED",
      "doc_id": "06192042",
      "has_document": true,
      "fee": "$240.00"
    },
    {
      "date_filed": "2018-02-21 15:47:08",
      "description": "MINI MINUTES FOR FEB-21-2018 01:30 PM FOR DEPT 501",
      "doc_id": null,
      "has_document": false,
      "fee": ""
    },
    {
      "date_filed": "2018-02-21 15:47:11",
      "description": "SETTLEMENT CONFERENCE HELD, CASE NOT SETTLED. THE PARTIES ENTER INTO A SIGNED AGREEMENT, WHICH WAS FILED. THE TRIAL DATE OF FEBRUARY 26, 2018 IS VACATED. (501)",
      "doc_id": null,
      "has_document": false,
      "fee": ""
    },
    {
      "date_filed": "2018-02-21 15:51:34",
      "description": "REMOVED FROM UD JURY CALENDAR SET FOR FEB-26-2018 - CASE SETTLED.",
      "doc_id": null,
      "has_document": false,
      "fee": ""
    },
    {
      "date_filed": "2018-03-08 15:58:28",
      "description": "EX PARTE APPLICATION FOR ORDER FOR ENTRY OF JUDGMENT PURSUANT TO SETTLEMENT AGREEMENT FILED BY PLAINTIFF THE TIDES CENTER",
      "doc_id": "06247145",
      "has_document": true,
      "fee": "$60.00"
    },
    {
      "date_filed": "2018-04-02 16:17:27",
      "description": "NOTICE OF ENTRY OF JUDGMENT",
      "doc_id": "06278452",
      "has_document": true,
      "fee": ""
    }
  ],
  "documents": [
    {
      "doc_id": "06192038",
      "description": "NOTICE TO DEFENDANTS",
      "filed": "2018-01-25",
      "is_available": true,
      "sha256": null,
      "byte_capture_deferred": true,
      "byte_capture_deferred_reason": "docket_only_mass_scan_requested",
      "byte_capture_scope": "docket-only"
    },
    {
      "doc_id": "06295530",
      "description": "DECLARATION OF FAIR RENTAL VALUE OF THE PREMISE WAS $15.26 FILED BY PLAINTIFF THE TIDES CENTER",
      "filed": "2018-04-13",
      "is_available": true,
      "sha256": null,
      "byte_capture_deferred": true,
      "byte_capture_deferred_reason": "docket_only_mass_scan_requested",
      "byte_capture_scope": "docket-only"
    },
    {
      "doc_id": "06225956",
      "description": "NOTICE OF LIMITED SCOPE REPRESENTATION, U.D. SETTLEMENT CONFERENCE AT 2/21/18 MANDATORY SETTLEMENT CONFERENCE FILED BY DEFENDANT COOPER, LISA KATAYAMA, ERIN ASSIGNED TO REPRESENT PARTY FOR U. D. SETTLEMENT CONFERENCE",
      "filed": "2018-02-21",
      "is_available": true,
      "sha256": null,
      "byte_capture_deferred": true,
      "byte_capture_deferred_reason": "docket_only_mass_scan_requested",
      "byte_capture_scope": "docket-only"
    },
    {
      "doc_id": "06195537",
      "description": "ANSWER TO COMPLAINT FILED BY DEFENDANT COOPER, LISA",
      "filed": "2018-01-29",
      "is_available": true,
      "sha256": null,
      "byte_capture_deferred": true,
      "byte_capture_deferred_reason": "docket_only_mass_scan_requested",
      "byte_capture_scope": "docket-only"
    },
    {
      "doc_id": "06195538",
      "description": "DEMAND FOR JURY FILED BY DEFENDANT COOPER, LISA",
      "filed": "2018-01-29",
      "is_available": true,
      "sha256": null,
      "byte_capture_deferred": true,
      "byte_capture_deferred_reason": "docket_only_mass_scan_requested",
      "byte_capture_scope": "docket-only"
    },
    {
      "doc_id": "06207991",
      "description": "DEMAND FOR JURY ON REQUEST TO SET CASE FOR JURY TRIAL FILED BY PLAINTIFF THE TIDES CENTER HEARING SET FOR FEB-26-2018 AT 09:00 AM IN DEPT 501",
      "filed": "2018-02-06",
      "is_available": true,
      "sha256": null,
      "byte_capture_deferred": true,
      "byte_capture_deferred_reason": "docket_only_mass_scan_requested",
      "byte_capture_scope": "docket-only"
    },
    {
      "doc_id": "06207992",
      "description": "NOTICE OF TIME AND PLACE OF TRIAL AND SETTLEMENT HEARING HEARING SET FOR FEB-21-2018 AT 01:30 PM IN DEPT 501",
      "filed": "2018-02-06",
      "is_available": true,
      "sha256": null,
      "byte_capture_deferred": true,
      "byte_capture_deferred_reason": "docket_only_mass_scan_requested",
      "byte_capture_scope": "docket-only"
    },
    {
      "doc_id": "06226837",
      "description": "STIPULATION FOR ENTRY OF JUDGMENT FILED BY PLAINTIFF THE TIDES CENTER ALSO FILED BY DEFENDANT COOPER, LISA",
      "filed": "2018-02-21",
      "is_available": true,
      "sha256": null,
      "byte_capture_deferred": true,
      "byte_capture_deferred_reason": "docket_only_mass_scan_requested",
      "byte_capture_scope": "docket-only"
    },
    {
      "doc_id": "06247863",
      "description": "DECLARATION OF LISA COOPER FILED BY DEFENDANT COOPER, LISA",
      "filed": "2018-03-09",
      "is_available": true,
      "sha256": null,
      "byte_capture_deferred": true,
      "byte_capture_deferred_reason": "docket_only_mass_scan_requested",
      "byte_capture_scope": "docket-only"
    },
    {
      "doc_id": "06263111",
      "description": "ORDER GRANTING PLAINTIFF'S EX PARTE APPLICATION FOR JUDGMENT",
      "filed": "2018-03-23",
      "is_available": true,
      "sha256": null,
      "byte_capture_deferred": true,
      "byte_capture_deferred_reason": "docket_only_mass_scan_requested",
      "byte_capture_scope": "docket-only"
    },
    {
      "doc_id": "06263170",
      "description": "THE COURT ORDERED THE FOLLOWING JUDGMENT ENTERED: IT IS ADJUDGED THAT PLAINTIFF THE TIDES CENTER RECOVER FROM DEFENDANT COOPER, LISA THE RESTITUTION AND POSSESSION OF THE PREMISES: 520 JONES STREET, #709, CITY AND COUNTY OF SAN FRANCISCO, CA 94102 $1,588.44 RENT, TOTAL JUDGMENT $1,588.44, LEASE FORFEITED, SEE SCANNED DOC",
      "filed": "2018-03-23",
      "is_available": true,
      "sha256": null,
      "byte_capture_deferred": true,
      "byte_capture_deferred_reason": "docket_only_mass_scan_requested",
      "byte_capture_scope": "docket-only"
    },
    {
      "doc_id": "06278451",
      "description": "NOTICE OF ENTRY OF ORDER/NOTICE OF RULING FILED GRANTING EX PARTE APPL FOR JUDGMNT FILED BY PLAINTIFF THE TIDES CENTER",
      "filed": "2018-04-02",
      "is_available": true,
      "sha256": null,
      "byte_capture_deferred": true,
      "byte_capture_deferred_reason": "docket_only_mass_scan_requested",
      "byte_capture_scope": "docket-only"
    },
    {
      "doc_id": "06330530",
      "description": "RETURN OF EXECUTION FOR POSSESSION OF REAL PROPERTY ISSUED TO SAN FRANCISCO COUNTY, RETURNED AND FILED, SATISFIED AS TO REAL PROPERTY ONLY AS TO DEFENDANT COOPER, LISA",
      "filed": "2018-05-09",
      "is_available": true,
      "sha256": null,
      "byte_capture_deferred": true,
      "byte_capture_deferred_reason": "docket_only_mass_scan_requested",
      "byte_capture_scope": "docket-only"
    },
    {
      "doc_id": "06192042",
      "description": "UNLAWFUL DETAINER - RESIDENTIAL, COMPLAINT FILED BY PLAINTIFF THE TIDES CENTER AS TO DEFENDANT COOPER, LISA DOES 1 TO 5 SUMMONS ISSUED, JUDICIAL COUNCIL CIVIL CASE COVER SHEET FILED",
      "filed": "2018-01-25",
      "is_available": true,
      "sha256": null,
      "byte_capture_deferred": true,
      "byte_capture_deferred_reason": "docket_only_mass_scan_requested",
      "byte_capture_scope": "docket-only"
    },
    {
      "doc_id": "06247145",
      "description": "EX PARTE APPLICATION FOR ORDER FOR ENTRY OF JUDGMENT PURSUANT TO SETTLEMENT AGREEMENT FILED BY PLAINTIFF THE TIDES CENTER",
      "filed": "2018-03-08",
      "is_available": true,
      "sha256": null,
      "byte_capture_deferred": true,
      "byte_capture_deferred_reason": "docket_only_mass_scan_requested",
      "byte_capture_scope": "docket-only"
    },
    {
      "doc_id": "06278452",
      "description": "NOTICE OF ENTRY OF JUDGMENT",
      "filed": "2018-04-02",
      "is_available": true,
      "sha256": null,
      "byte_capture_deferred": true,
      "byte_capture_deferred_reason": "docket_only_mass_scan_requested",
      "byte_capture_scope": "docket-only"
    }
  ],
  "parties": [
    {
      "name": "COOPER, LISA 520 JONES ST., #709 SAN FRANCISCO, CA 94102",
      "party_type": "DEFENDANT",
      "attorneys": [],
      "self_represented": true,
      "raw_attorney_texts": [
        "Pro Per"
      ]
    },
    {
      "name": "DOES 1 TO 5 520 JONES ST., #709 SAN FRANCISCO, CA 94102",
      "party_type": "DEFENDANT",
      "attorneys": [],
      "self_represented": false
    },
    {
      "name": "THE TIDES CENTER",
      "party_type": "PLAINTIFF",
      "attorneys": [
        "ZANGHI, JOHN P"
      ],
      "self_represented": false
    }
  ],
  "attorneys": [
    {
      "name": "ZANGHI, JOHN P",
      "bar_number": "145845",
      "address": "ZANGHI TORRES ARSHAWSKY LLP, 625 MARKET STREET, 4TH FLOOR, SAN FRANCISCO, CALIFORNIA 94105, 415-977-0444",
      "parties_represented": [
        "THE TIDES CENTER (PLAINTIFF)"
      ]
    }
  ],
  "calendar": [
    {
      "court_date": "2018-02-26 9:00 AM",
      "matters": "UD JURY TRIALS<br>Off Calendar Feb-21-2018 Off Calendar",
      "location": "CIVIC CENTER COURTHOUSE ROOM 501",
      "judge": "RONALD E. QUIDACHAY"
    },
    {
      "court_date": "2018-02-21 1:30 PM",
      "matters": "OTHER SETTLEMENT CONFERENCE<br>Off Calendar Feb-21-2018 Off Calendar<br>MINI MINUTES: Judge Pro Tem: Dianne Peebles, Clerk: E. Larnauti, Not Reported. (D501/JPT)<br><br>Appearances:<br>Plaintiff The Tides Center is present, represented by Georgetta Lovett. <br>Attorney John P. Zanghi for the plaintiff.<br>Defendant Lisa Cooper is present.<br>Attorney Erin Katayama appearing for defendant in limited scope.<br><br>The Judge Pro Tem, litigants and counsel confer for settlement discussions. This case settled. The parties enter into a signed agreement, which was filed. The trial date of February 26, 2018 is vacated.<br>",
      "location": "CIVIC CENTER COURTHOUSE ROOM 501",
      "judge": "RONALD E. QUIDACHAY"
    }
  ],
  "payments": [
    {
      "date": "2018-01-25",
      "amount": 240,
      "type": "CHECK",
      "receipt": "W1518125F013",
      "description": "FIRST FILING UD COMPLT 2,500-10,000"
    },
    {
      "date": "2018-01-29",
      "amount": 0,
      "type": "IFP",
      "receipt": "W1518129F002",
      "description": "FIRST PAPER RESPONSE/PLEADING $2,500 - $10,000"
    },
    {
      "date": "2018-03-08",
      "amount": 60,
      "type": "CREDIT CARD",
      "receipt": "W2118308M005",
      "description": "MOTION"
    },
    {
      "date": "2018-04-13",
      "amount": 25,
      "type": "CHECK",
      "receipt": "W2018413W004",
      "description": "WRIT ISSUED"
    }
  ],
  "payments_total": 325,
  "method_status": {
    "GetPayments": "ok",
    "GetAttorneys": "ok",
    "GetDocuments": "ok",
    "GetCalendar": "ok",
    "GetROA": "ok",
    "GetParties": "ok"
  },
  "document_bytes_captured": true,
  "document_byte_capture_scope": "docket-only",
  "documents_bytes_count": 0,
  "documents_unavailable_count": 0,
  "documents_deferred_count": 16
}
